walkie_code/__init__.py
walkie_code/cli.py
walkie_code/config.py
walkie_code/session.py
walkie_code/websocket_client.py
walkie_code-0.2.2.dist-info/METADATA
walkie_code-0.2.2.dist-info/WHEEL
walkie_code-0.2.2.dist-info/entry_points.txt
walkie_code-0.2.2.dist-info/top_level.txt
walkie_code-0.2.2.dist-info/RECORD
