Metadata-Version: 2.4
Name: walkie_code
Version: 0.2.2
Summary: Desktop client for WalkieCode with AI tool use - read/write files, run commands, search code
Author: WalkieCode Team
License: MIT
Keywords: claude,ai,websocket,desktop
Classifier: Development Status :: 4 - Beta
Classifier: Environment :: Console
Classifier: Intended Audience :: Developers
Classifier: License :: OSI Approved :: MIT License
Classifier: Operating System :: OS Independent
Classifier: Programming Language :: Python :: 3
Classifier: Programming Language :: Python :: 3.9
Classifier: Programming Language :: Python :: 3.10
Classifier: Programming Language :: Python :: 3.11
Classifier: Programming Language :: Python :: 3.12
Classifier: Topic :: Software Development :: User Interfaces
Requires-Python: >=3.9
Requires-Dist: websocket-client>=1.6.0
Requires-Dist: certifi>=2023.0.0
Requires-Dist: anthropic>=0.39.0
Provides-Extra: test
Requires-Dist: pytest>=7.0.0; extra == "test"
Requires-Dist: pytest-mock>=3.10.0; extra == "test"
